.gitignore
AUTHORS.txt
CONTRIBUTING.md
INSTALL.md
LICENSE
LICENSE.txt
README.md
example.py
setup.cfg
setup.py
.github/ISSUE_TEMPLATE/bug_report.md
.github/ISSUE_TEMPLATE/feature_request.md
.github/workflows/pythonapp.yml
doc/Makefile
doc/make.bat
doc/source/api.rst
doc/source/conf.py
doc/source/examples.rst
doc/source/flower.rst
doc/source/getting_started.rst
doc/source/index.rst
doc/source/installation.rst
kivy_garden.ebs.cefkivy.egg-info/PKG-INFO
kivy_garden.ebs.cefkivy.egg-info/SOURCES.txt
kivy_garden.ebs.cefkivy.egg-info/dependency_links.txt
kivy_garden.ebs.cefkivy.egg-info/requires.txt
kivy_garden.ebs.cefkivy.egg-info/top_level.txt
kivy_garden/ebs/__init__.py
kivy_garden/ebs/cefkivy/__init__.py
kivy_garden/ebs/cefkivy/browser.py
kivy_garden/ebs/cefkivy/popup.kv
kivy_garden/ebs/cefkivy/popup.py
kivy_garden/ebs/cefkivy/components/__init__.py
kivy_garden/ebs/cefkivy/components/blockdialog.py
kivy_garden/ebs/cefkivy/components/dialog.py
kivy_garden/ebs/cefkivy/components/jsdialog.py
kivy_garden/ebs/cefkivy/components/keyboard.py
kivy_garden/ebs/cefkivy/components/keyboard_trigger.js
kivy_garden/ebs/cefkivy/handlers/__init__.py
kivy_garden/ebs/cefkivy/handlers/base.py
kivy_garden/ebs/cefkivy/handlers/display.py
kivy_garden/ebs/cefkivy/handlers/download.py
kivy_garden/ebs/cefkivy/handlers/jsdialog.py
kivy_garden/ebs/cefkivy/handlers/keyboard.py
kivy_garden/ebs/cefkivy/handlers/lifespan.py
kivy_garden/ebs/cefkivy/handlers/load.py
kivy_garden/ebs/cefkivy/handlers/render.py
kivy_garden/ebs/cefkivy/handlers/request.py
kivy_garden/ebs/cefkivy/inputs/__init__.py
kivy_garden/ebs/cefkivy/inputs/keyboard.py
kivy_garden/ebs/cefkivy/inputs/keycodes.py
kivy_garden/ebs/cefkivy/inputs/touch.py
kivy_garden/ebs/cefkivy/mixins/__init__.py
kivy_garden/ebs/cefkivy/mixins/cookies.py
kivy_garden/ebs/cefkivy/mixins/dialogs.py
kivy_garden/ebs/cefkivy/mixins/jsbindings.py
kivy_garden/ebs/cefkivy/mixins/keyboard.py
kivy_garden/ebs/cefkivy/mixins/navigation.py
kivy_garden/ebs/cefkivy/mixins/popup.py
kivy_garden/ebs/cefkivy/mixins/security.py
kivy_garden/ebs/cefkivy/mixins/touch.py
tools/hooks/pre-commit