Metadata-Version: 2.1
Name: kivy-garden.ebs.cefkivy
Version: 66.0.13
Summary: CEF Browser widget for Kivy
Home-page: https://github.com/ebs-universe/kivy_garden.ebs.cefkivy
Author: Chintalagiri Shashank
Author-email: shashank@chintal.in
License: UNKNOWN
Project-URL: Bug Reports, https://github.com/ebs-universe/kivy_garden.ebs.cefkivy/issues
Project-URL: Source, https://github.com/ebs-universe/kivy_garden.ebs.cefkivy
Keywords: Kivy kivy-garden
Platform: UNKNOWN
Classifier: Development Status :: 4 - Beta
Classifier: Intended Audience :: Developers
Classifier: Topic :: Software Development :: Libraries
Classifier: License :: OSI Approved :: MIT License
Classifier: Programming Language :: Python :: 3.5
Classifier: Programming Language :: Python :: 3.6
Classifier: Programming Language :: Python :: 3.7
Requires-Python: >=3.4, <3.8
Provides-Extra: dev
Provides-Extra: ci
